aioaeroflex/__init__.py
aioaeroflex/aeroflex_bed.py
aioaeroflex/py.typed
aioaeroflex-0.1.0.dist-info/METADATA
aioaeroflex-0.1.0.dist-info/WHEEL
aioaeroflex-0.1.0.dist-info/licenses/LICENSE
aioaeroflex-0.1.0.dist-info/RECORD
