Metadata-Version: 2.4
Name: aioaeroflex
Version: 0.1.0
Summary: Async Python library for controlling Aeroflex adjustable beds via Bluetooth
Project-URL: Homepage, https://github.com/iddora/aioaeroflex
Project-URL: Bug Tracker, https://github.com/iddora/aioaeroflex/issues
Author-email: Iddo Rachlewski <github@rachlewski.com>
License-File: LICENSE
Classifier: Development Status :: 3 - Alpha
Classifier: Framework :: AsyncIO
Classifier: License :: OSI Approved :: Apache Software License
Classifier: Operating System :: OS Independent
Classifier: Programming Language :: Python :: 3
Requires-Python: >=3.7
Requires-Dist: bleak>=0.21.1
